{
  "new york": "New York",
  "berlin": "Berlin",
  "tokyo": "Tokyo",
  "los angeles": "Los Angeles",
  "toronto": "Toronto",
  "madrid": "Madrid",
  "sydney": "Sydney",
  "moscow": "Moscow",
  "chicago": "Chicago",
  "amsterdam": "Amsterdam",
  "vienna": "Vienna",
  "rome": "Rome",
  "san francisco": "San Francisco",
  "barcelona": "Barcelona",
  "oslo": "Oslo",
  "copenhagen": "Copenhagen",
  "lisbon": "Lisbon",
  "stockholm": "Stockholm",
  "prague": "Prague",
  "dublin": "Dublin",
  "brussels": "Brussels",
  "seoul": "Seoul",
  "helsinki": "Helsinki",
  "mexico city": "Mexico City",
  "buenos aires": "Buenos Aires",
  "athens": "Athens",
  "hong kong": "Hong Kong",
  "dubai": "Dubai",
  "istanbul": "Istanbul",
  "jakarta": "Jakarta",
  "cairo": "Cairo",
  "bangkok": "Bangkok",
  "singapore": "Singapore",
  "kuala lumpur": "Kuala Lumpur",
  "manila": "Manila",
  "beijing": "Beijing",
  "shanghai": "Shanghai",
  "mumbai": "Mumbai",
  "delhi": "Delhi",
  "karachi": "Karachi",
  "paris": "Paris",
  "london": "London",
  "tomorrow": "tomorrow",
  "kyiv": "Kyiv",
  "the day after tomorrow": "the day after tomorrow",
  "two days": "two days",
  "three days": "three days",
  "four days": "four days",
  "five days": "five days",
  "six days": "six days",
  "next monday": "next Monday",
  "seven days": "seven days"
}